{
 "open": false,
 "alternate": false,
 "junior": true,
 "pointscore": true,
 "start": "Mass",
 "eventId": "342",
 "id": "1143",
 "placeTimes": [
  "0:07:29.00",
  "0:07:33.00",
  "0:07:34.00",
  "0:07:41.00",
  "0:07:48.00",
  "0:07:51.00",
  "0:07:52.00",
  "0:07:53.00",
  "0:08:10.00",
  "0:08:27.00",
  "0:08:58.00",
  "0:09:06.00",
  "0:09:08.00",
  "0:09:15.00",
  "0:09:38.00",
  "0:09:51.00",
  "0:10:00.00",
  "0:10:18.00",
  "0:10:43.00",
  "0:10:48.00",
  "0:11:38.00",
  "0:11:58.00",
  "0:13:43.00",
  "0:14:08.00"
 ],
 "placeContacts": [
  "2012",
  "2104",
  "1983",
  "2247",
  "1992",
  "692",
  "2015",
  "690",
  "1955",
  "2285",
  "2339",
  "796",
  "2227",
  "1695",
  "1986",
  "1713",
  "2446",
  "1058",
  "1696",
  "1947",
  "2221",
  "2228",
  "791",
  "2223"
 ],
 "courseId": "94"
}