{
 "open": true,
 "alternate": false,
 "junior": false,
 "pointscore": false,
 "start": "Mass",
 "eventId": "374",
 "id": "1245",
 "placeTimes": [
  "0:05:02.40",
  "0:05:16.20",
  "0:05:27.30",
  "0:05:34.50",
  "0:05:38.50",
  "0:05:53.70",
  "0:05:54.70",
  "0:06:18.70",
  "0:06:39.80",
  "0:06:57.40",
  "0:07:00.70",
  "0:08:12.40",
  "0:08:19.20",
  "0:08:19.40"
 ],
 "placeContacts": [
  "1946",
  "564",
  "1886",
  "556",
  "2079",
  "1660",
  "1301",
  "998",
  "207",
  "1982",
  "2109",
  "2219",
  "2239",
  "2229"
 ],
 "courseId": "20"
}