{
 "open": true,
 "alternate": false,
 "junior": false,
 "pointscore": false,
 "start": "Mass",
 "eventId": "534",
 "id": "1773",
 "placeTimes": [
  "0:00:31.30",
  "0:00:32.00",
  "0:00:33.20",
  "0:00:37.40",
  "0:00:38.00",
  "0:00:39.50",
  "0:00:39.90",
  "0:00:41.00",
  "0:00:41.20",
  "0:00:41.80",
  "0:00:45.70",
  "0:00:49.30",
  "0:00:52.40",
  "0:01:03.30"
 ],
 "placeContacts": [
  "2002",
  "2073",
  "1301",
  "2781",
  "2707",
  "2684",
  "2690",
  "2696",
  "2243",
  "1299",
  "2693",
  "2699",
  "2254",
  "2678"
 ],
 "courseId": "6"
}