{
 "open": false,
 "alternate": true,
 "junior": false,
 "pointscore": true,
 "start": "Mass",
 "eventId": "115",
 "id": "342",
 "placeTimes": [
  "0:14:06.00",
  "0:14:23.00",
  "0:14:41.00",
  "0:14:42.00",
  "0:15:12.00",
  "0:15:17.00",
  "0:15:48.00",
  "0:16:20.00",
  "0:16:33.00",
  "0:16:44.00",
  "0:16:54.00",
  "0:17:52.00",
  "0:18:25.00",
  "0:18:25.00",
  "0:18:34.00",
  "0:18:46.00",
  "0:18:49.00",
  "0:19:40.00",
  "0:19:51.00",
  "0:20:27.00",
  "0:20:27.00",
  "0:21:26.00",
  "0:21:41.00",
  "0:22:04.00",
  "0:22:39.00",
  "0:22:58.00",
  "0:23:05.00",
  "0:23:16.00",
  "0:24:03.00",
  "0:24:19.00",
  "0:25:34.00",
  "0:26:55.00",
  "0:27:26.00"
 ],
 "placeContacts": [
  "32",
  "175",
  "581",
  "842",
  "308",
  "245",
  "911",
  "50",
  "1397",
  "83",
  "191",
  "908",
  "323",
  "34",
  "1250",
  "352",
  "65",
  "508",
  "70",
  "60",
  "48",
  "51",
  "1398",
  "743",
  "143",
  "1399",
  "1400",
  "866",
  "156",
  "938",
  "1373",
  "1009",
  "1374"
 ],
 "courseId": "69"
}