{
 "open": true,
 "alternate": false,
 "junior": false,
 "pointscore": false,
 "start": "Mass",
 "eventId": "184",
 "id": "593",
 "placeTimes": [
  "0:00:41.70",
  "0:00:42.70",
  "0:00:44.60",
  "0:00:48.20",
  "0:00:50.30",
  "0:00:54.30",
  "0:00:56.60",
  "0:00:57.60",
  "0:00:58.10",
  "0:00:58.40",
  "0:00:58.60",
  "0:00:59.50",
  "0:01:00.60"
 ],
 "placeContacts": [
  "94",
  "1759",
  "83",
  "392",
  "1301",
  "1019",
  "1660",
  "1066",
  "610",
  "729",
  "727",
  "23",
  "556"
 ],
 "courseId": "8"
}