{
 "open": true,
 "alternate": false,
 "junior": false,
 "pointscore": false,
 "start": "Mass",
 "eventId": "251",
 "id": "825",
 "placeTimes": [
  "0:04:34.70",
  "0:05:25.40",
  "0:05:25.90",
  "0:05:31.80",
  "0:05:33.70",
  "0:05:39.40",
  "0:05:41.70",
  "0:06:15.10",
  "0:06:34.80",
  "0:06:49.70",
  "0:07:09.00",
  "0:07:17.40",
  "0:07:42.20"
 ],
 "placeContacts": [
  "641",
  "1099",
  "1942",
  "556",
  "1906",
  "725",
  "740",
  "168",
  "1408",
  "54",
  "17",
  "198",
  "1807"
 ],
 "courseId": "18"
}